LAB8/q3_b.v
module d_flip_flop_3b (clk,reset,preset,d,q);
input clk,reset,preset,d;
output reg q;
always @(posedge clk or negedge reset or negedge preset) begin
if (!reset)
q <= 0;
else if (!preset)
q <= 1;
else
q <= d;
end
endmodule
`timescale 1ns/1ns
module tb_d_flip_flop_3b;
reg clk, reset, preset, d;
wire q;
d_flip_flop_3b uut (clk,reset,preset,d,q);
initial begin
clk = 0;
forever #5 clk = ~clk;
end
initial begin
reset = 0;
preset=0;
d=0;
#10 reset = 1;
d = 1;
#10 d = 0;
d = 0;
#10 d = 1;
preset = 0;
#10 preset = 1;
reset = 0;
d = 1;
#10 d = 0;
#10 reset = 1;
#10 $finish;
end
initial begin
$dumpfile("tb_d_flip_flop_3b.vcd");
$dumpvars(0, tb_d_flip_flop_3b);
end
endmodule

LAB8/tb_d_flip_flop_3b.vcd
$date
	Mon Nov 27 23:21:39 2023
$end
$version
	Icarus Verilog
$end
$timescale
	1ns
$end
$scope module tb_d_flip_flop_3b $end
$var wire 1 ! q $end
$var reg 1 " clk $end
$var reg 1 # d $end
$var reg 1 $ preset $end
$var reg 1 % reset $end
$scope module uut $end
$var wire 1 " clk $end
$var wire 1 # d $end
$var wire 1 $ preset $end
$var wire 1 % reset $end
$var reg 1 ! q $end
$upscope $end
$upscope $end
$enddefinitions $end
#0
$dumpvars
0%
0$
0#
0"
0!
$end
#5
1"
#10
0"
1#
1%
#15
1!
1"
#20
0"
0#
#25
1"
#30
0"
1#
#35
1"
#40
0!
0"
0%
1$
#45
1"
#50
0"
0#
#55
1"
#60
0"
1%
