LAB1/lab1_full_half.v
module half_adder(sum, carry, a, b);
input a, b;
output sum, carry;
xor g1(sum, a, b);
and g2(carry, a, b);
endmodule

module full_adder(sum, cout, a, b, cin);
input a, b, cin;
output sum, cout;
wire s1, c1, c2;
half_adder ha1(s1,c1,a,b);
half_adder ha2(sum,c2,cin,s1);
or g1(cout,c1,c2);
endmodule


// module full_adder_tb;
//     reg a, b, cin;
//     wire sum, cout;

//     full_adder uut (.a(a),.b(b),.cin(cin),.sum(sum),.cout(cout));
//     // Testbench behavior
//     initial begin
//         $dumpfile("half_full_adder.vcd");
//         $dumpvars(0, full_adder_tb);
//         #10;
//         a = 0; b = 0; cin = 0;
//         #10 $display("Input: a=%b, b=%b, cin=%b, sum=%b, cout=%b", a,b, cin, sum, cout);
//         a = 0; b = 0; cin = 1;
//         #10 $display("Input: a=%b, b=%b, cin=%b, sum=%b, cout=%b", a,b, cin, sum, cout);
//         a = 0; b = 1; cin = 0;
//         #10 $display("Input: a=%b, b=%b, cin=%b, sum=%b, cout=%b", a,b, cin, sum, cout);
//         a = 0; b = 1; cin = 1;
//         #10 $display("Input: a=%b, b=%b, cin=%b, sum=%b, cout=%b", a,b, cin, sum, cout);
//         a = 1; b = 0; cin = 0;
//         #10 $display("Input: a=%b, b=%b, cin=%b, sum=%b, cout=%b", a,b, cin, sum, cout);
//         a = 1; b = 0; cin = 1;
//         #10 $display("Input: a=%b, b=%b, cin=%b, sum=%b, cout=%b", a,b, cin, sum, cout);
//         a = 1; b = 1; cin = 0;
//         #10 $display("Input: a=%b, b=%b, cin=%b, sum=%b, cout=%b", a,b, cin, sum, cout);
//         a = 1; b = 1; cin = 1;
//         #10 $display("Input: a=%b, b=%b, cin=%b, sum=%b, cout=%b", a,b, cin, sum, cout);
        
//         $finish; 
//         end
// endmodule

LAB1/lab1_full_half_tb.v
`include "lab1_full_half.v"

module full_adder_tb;
    reg a, b, cin;
    wire sum, cout;

    full_adder uut (.a(a),.b(b),.cin(cin),.sum(sum),.cout(cout));
    // Testbench behavior
    initial begin
        $dumpfile("half_full_adder.vcd");
        $dumpvars(0, full_adder_tb);
        #10;
        a = 0; b = 0; cin = 0;
        #10 $display("Input: a=%b, b=%b, cin=%b, sum=%b, cout=%b", a,b, cin, sum, cout);
        a = 0; b = 0; cin = 1;
        #10 $display("Input: a=%b, b=%b, cin=%b, sum=%b, cout=%b", a,b, cin, sum, cout);
        a = 0; b = 1; cin = 0;
        #10 $display("Input: a=%b, b=%b, cin=%b, sum=%b, cout=%b", a,b, cin, sum, cout);
        a = 0; b = 1; cin = 1;
        #10 $display("Input: a=%b, b=%b, cin=%b, sum=%b, cout=%b", a,b, cin, sum, cout);
        a = 1; b = 0; cin = 0;
        #10 $display("Input: a=%b, b=%b, cin=%b, sum=%b, cout=%b", a,b, cin, sum, cout);
        a = 1; b = 0; cin = 1;
        #10 $display("Input: a=%b, b=%b, cin=%b, sum=%b, cout=%b", a,b, cin, sum, cout);
        a = 1; b = 1; cin = 0;
        #10 $display("Input: a=%b, b=%b, cin=%b, sum=%b, cout=%b", a,b, cin, sum, cout);
        a = 1; b = 1; cin = 1;
        #10 $display("Input: a=%b, b=%b, cin=%b, sum=%b, cout=%b", a,b, cin, sum, cout);
        
        $finish; 
        end
endmodule

LAB1/half_full_adder.vcd
$date
	Fri Sep 29 13:39:17 2023
$end
$version
	Icarus Verilog
$end
$timescale
	1s
$end
$scope module full_adder_tb $end
$var wire 1 ! sum $end
$var wire 1 " cout $end
$var reg 1 # a $end
$var reg 1 $ b $end
$var reg 1 % cin $end
$scope module uut $end
$var wire 1 # a $end
$var wire 1 $ b $end
$var wire 1 % cin $end
$var wire 1 " cout $end
$var wire 1 ! sum $end
$var wire 1 & s1 $end
$var wire 1 ' c2 $end
$var wire 1 ( c1 $end
$scope module ha1 $end
$var wire 1 # a $end
$var wire 1 $ b $end
$var wire 1 ( carry $end
$var wire 1 & sum $end
$upscope $end
$scope module ha2 $end
$var wire 1 % a $end
$var wire 1 & b $end
$var wire 1 ' carry $end
$var wire 1 ! sum $end
$upscope $end
$upscope $end
$upscope $end
$enddefinitions $end
#0
$dumpvars
x(
x'
x&
x%
x$
x#
x"
x!
$end
#10
0"
0!
0'
0&
0(
0%
0$
0#
#20
1!
1%
#30
1&
0%
1$
#40
1"
0!
1'
1%
#50
0"
1!
0'
0%
0$
1#
#60
1"
0!
1'
1%
#70
0'
0&
1(
0%
1$
#80
1!
1%
