LAB1/lab1_q1.v
// STRUCTURAL LEVEL 
// module lab1_q1(out,v1,v2,v3);

// input v1,v2,v3;
// output out;
// wire w1,w2,w3;

// and(w1,v1,v2);
// and(w2,v2,v3);
// and(w3,v1,v3);

// or(out,w1,w2,w3);

// endmodule



//REGISTER TRANSFER LEVEL
// module lab1_q1(out,v1,v2,v3);

// input v1,v2,v3;
// output out;

// assign out = (v1 & v2) | (v2 & v3) | (v1 & v3);

// endmodule


//BEHAVIORAL LEVEL
module lab1_q1(out,v1,v2,v3);

input v1,v2,v3;
output reg out;

always @(v1, v2, v3) 
    begin
        if ((v1 & & v2) | | (v2 & & v3) | | (v3 & & v1))
            out = 1; 
        else
            out = 0; 
    end

endmodule

LAB1/lab1_q1_tb.v
`include "lab1_q1.v";
module lab1_q1_tb;

reg v1,v2,v3;
wire out;

lab1_q1 obj(.out(out),.v1(v1),.v2(v2),.v3(v3));

initial 
    begin 
        $dumpfile("lab1_q1.vcd");
        $dumpvars(0,lab1_q1_tb);

        #10;
        
        v1 = 0; v2 = 0; v3 = 0;
        #10 $display("Input: v1=%b, v2=%b, v3=%b, Output: out=%b", v1, v2,v3, out);

        v1 = 0; v2 = 0; v3 = 1;
        #10 $display("Input: v1=%b, v2=%b, v3=%b, Output: out=%b", v1, v2,v3, out);

        v1 = 0; v2 = 1; v3 = 0;
        #10 $display("Input: v1=%b, v2=%b, v3=%b, Output: out=%b", v1, v2,v3, out);

        v1 = 1; v2 = 0; v3 = 0;
        #10 $display("Input: v1=%b, v2=%b, v3=%b, Output: out=%b", v1, v2,v3, out);

        v1 = 0; v2 = 1; v3 = 1;
        #10 $display("Input: v1=%b, v2=%b, v3=%b, Output: out=%b", v1, v2,v3, out);

        v1 = 1; v2 = 1; v3 = 0;
        #10 $display("Input: v1=%b, v2=%b, v3=%b, Output: out=%b", v1, v2,v3, out);

        v1 = 0; v2 = 1; v3 = 1;
        #10 $display("Input: v1=%b, v2=%b, v3=%b, Output: out=%b", v1, v2,v3, out);

        v1 = 1; v2 = 0; v3 = 1;
        #10 $display("Input: v1=%b, v2=%b, v3=%b, Output: out=%b", v1, v2,v3, out);

        v1 = 1; v2 = 1; v3 = 1;
        #10 $display("Input: v1=%b, v2=%b, v3=%b, Output: out=%b", v1, v2,v3, out);

        $finish;

    end
endmodule

LAB1/lab1_q1.vcd
$date
	Tue Oct  3 11:45:03 2023
$end
$version
	Icarus Verilog
$end
$timescale
	1s
$end
$scope module lab1_q1_tb $end
$var wire 1 ! out $end
$var reg 1 " v1 $end
$var reg 1 # v2 $end
$var reg 1 $ v3 $end
$scope module obj $end
$var wire 1 " v1 $end
$var wire 1 # v2 $end
$var wire 1 $ v3 $end
$var reg 1 ! out $end
$upscope $end
$upscope $end
$enddefinitions $end
#0
$dumpvars
x$
x#
x"
x!
$end
#10
0!
0$
0#
0"
#20
1$
#30
0$
1#
#40
0#
1"
#50
1!
1$
1#
0"
#60
0$
1"
#70
1$
0"
#80
0#
1"
#90
1#
