LAB1/lab1_q2.v
module system1(out,v1,v2,v3);

input v1,v2,v3;
output out;
wire w1,w2,w3;

and g1(w1,v1,v2);
and g2(w2,v3,v2);
and g3(w3,v1,v3);
or g4(out,g1,g2,g3);

endmodule

module system2(outa,va,vb,vc);

input va,vb,vc;
output outa;
wire out;

system1 s1(out,va,vb,vc);
and g1(outa,out,1'b1);

endmodule

LAB1/lab1_q2_tb.v
`include "lab1_q2.v"
module system2_tb;

reg va, vb, vc;
wire outa;
    
    system2 uut (.outa(outa),.va(va),.vb(vb),.vc(vc));

    initial begin
        $dumpfile("lab1_q2_tb.vcd");
        $dumpvars(0, system2_tb);
        #10;

        va = 0; vb = 0; vc = 0;
        #10 $display("Input: va=%b, vb=%b, vc=%b, output: outa=%b", va, vb,vc, outa);

        va = 0; vb = 0; vc = 1;
        #10 $display("Input: va=%b, vb=%b, vc=%b, output: outa=%b", va, vb,vc, outa);

        va = 0; vb = 1; vc = 0;
        #10 $display("Input: va=%b, vb=%b, vc=%b, output: outa=%b", va, vb,vc, outa);

        va = 0; vb = 1; vc = 1;
        #10 $display("Input: va=%b, vb=%b, vc=%b, output: outa=%b", va, vb,vc, outa);

        va = 1; vb = 0; vc = 0;
        #10 $display("Input: va=%b, vb=%b, vc=%b, output: outa=%b", va, vb,vc, outa);

        va = 1; vb = 0; vc = 1;
        #10 $display("Input: va=%b, vb=%b, vc=%b, output: outa=%b", va, vb,vc, outa);

        va = 1; vb = 1; vc = 0;
        #10 $display("Input: va=%b, vb=%b, vc=%b, output: outa=%b", va, vb,vc, outa);

        va = 1; vb = 1; vc = 1;
        #10 $display("Input: va=%b, vb=%b, vc=%b, output: outa=%b", va, vb,vc, outa);

        $finish; 
        
        end
endmodule

LAB1/lab1_q2_tb.vcd
$date
	Sat Oct 14 23:43:02 2023
$end
$version
	Icarus Verilog
$end
$timescale
	1s
$end
$scope module system2_tb $end
$var wire 1 ! outa $end
$var reg 1 " va $end
$var reg 1 # vb $end
$var reg 1 $ vc $end
$scope module uut $end
$var wire 1 ! outa $end
$var wire 1 " va $end
$var wire 1 # vb $end
$var wire 1 $ vc $end
$var wire 1 % out $end
$scope module s1 $end
$var wire 1 & g1 $end
$var wire 1 ' g2 $end
$var wire 1 ( g3 $end
$var wire 1 % out $end
$var wire 1 " v1 $end
$var wire 1 # v2 $end
$var wire 1 $ v3 $end
$var wire 1 ) w1 $end
$var wire 1 * w2 $end
$var wire 1 + w3 $end
$upscope $end
$upscope $end
$upscope $end
$enddefinitions $end
#0
$dumpvars
x+
x*
x)
z(
z'
z&
x%
x$
x#
x"
x!
$end
#10
0*
0)
0+
0$
0#
0"
#20
1$
#30
0$
1#
#40
1*
1$
#50
0*
0$
0#
1"
#60
1+
1$
#70
0+
1)
0$
1#
#80
1*
1+
1$
