LAB4/q2_rtl.v
module ALU_4bit_dataflow (
    input [3:0] A,
    input [3:0] B,
    input [2:0] ALU_OP,
    output [3:0] out
);
assign out = (ALU_OP == 3'b000) ? A + B :
            (ALU_OP == 3'b001) ? A - B :
(ALU_OP == 3'b010) ? ~(A & B) :
(ALU_OP == 3'b011) ? ~(A | B) :
(ALU_OP == 3'b100) ? (A < B) ? 4'b1 : 4'b0:
(ALU_OP == 3'b101) ? (A == B) ? 4'b1 : 4'b0:
(ALU_OP == 3'b110) ? (B[1:0] == 2'b00) ? A : (B[1:0] == 2'b01)
? (A << 1) : (B[1:0] == 2'b10) ? (A << 2) : (A << 3) :
(ALU_OP == 3'b111) ? (B[1:0] == 2'b00) ? A : (B[1:0] == 2'b01)
? (A >> 1) : (B[1:0] == 2'b10) ? (A >> 2) : (A >> 3) : 4'bxxxx; // Default operation
endmodule



module lab4_q2a_tb();
reg[3:0]A,B;
reg[2:0]ALU_OP;
wire[3:0]out;
ALU_4bit_dataflow a1(A,B,ALU_OP,out);
initial
begin
    $dumpfile("ALU_RTL_dataflow.vcd");
    $dumpvars(0,lab4_q2a_tb);
    ALU_OP=3'b000;A=4'b1100;B=4'b0011;
    #10;
    ALU_OP=3'b001;A=4'b1100;B=4'b0011;
    #10;
    ALU_OP=3'b010;A=4'b1100;B=4'b0011;
    #10;
    ALU_OP=3'b011;A=4'b1100;B=4'b0010;
    #10;
    ALU_OP=3'b100;A=4'b0110;B=4'b0011;
    #10;
    ALU_OP=3'b101;A=4'b1010;B=4'b1010;
    #10;
    ALU_OP=3'b110;A=4'b1010;B=4'b0010;
    #10;
    ALU_OP=3'b111;A=4'b1010;B=4'b0010;
    #10;
end
initial begin
$monitor("ALU_OP = %b, A = %b, B = %b, out = %b",ALU_OP,A,B,out); end
endmodule

LAB4/ALU_RTL_dataflow.vcd
$date
	Mon Oct  9 23:03:42 2023
$end
$version
	Icarus Verilog
$end
$timescale
	1s
$end
$scope module lab4_q2a_tb $end
$var wire 4 ! out [3:0] $end
$var reg 4 " A [3:0] $end
$var reg 3 # ALU_OP [2:0] $end
$var reg 4 $ B [3:0] $end
$scope module a1 $end
$var wire 4 % A [3:0] $end
$var wire 3 & ALU_OP [2:0] $end
$var wire 4 ' B [3:0] $end
$var wire 4 ( out [3:0] $end
$upscope $end
$upscope $end
$enddefinitions $end
#0
$dumpvars
b1111 (
b11 '
b0 &
b1100 %
b11 $
b0 #
b1100 "
b1111 !
$end
#10
b1001 !
b1001 (
b1 #
b1 &
#20
b1111 !
b1111 (
b10 #
b10 &
#30
b1 !
b1 (
b10 $
b10 '
b11 #
b11 &
#40
b0 !
b0 (
b11 $
b11 '
b110 "
b110 %
b100 #
b100 &
#50
b1 !
b1 (
b1010 $
b1010 '
b1010 "
b1010 %
b101 #
b101 &
#60
b1000 !
b1000 (
b10 $
b10 '
b110 #
b110 &
#70
b10 !
b10 (
b111 #
b111 &
