Lab5/q3.v
`timescale 1us/1us
module full_adder(input a, b, cin, output sum, cout);
    assign {cout, sum} = a + b + cin;
endmodule

module q3_tb;
    reg a, b, cin;
    wire sum, cout;
    full_adder u1 (.a(a), .b(b), .cin(cin), .sum(sum), .cout(cout));
    initial begin
        $dumpfile("lab_q3.vcd");
        $dumpvars(0, q3_tb);
        #1 a = 1'b0; b = 1'b0; cin = 1'b0;
        #1 a = 1'b0; b = 1'b0; cin = 1'b1;
        #1 a = 1'b0; b = 1'b0; cin = 1'bx;
        #1 a = 1'b0; b = 1'b1; cin = 1'b0;
        #1 a = 1'b0; b = 1'b1; cin = 1'b1;
        #1 a = 1'b0; b = 1'b1; cin = 1'bx;
        #1 a = 1'b0; b = 1'bx; cin = 1'b0;
        #1 a = 1'b0; b = 1'bx; cin = 1'b1;
        #1 a = 1'b0; b = 1'bx; cin = 1'bx;
        #1 a = 1'b1; b = 1'b0; cin = 1'b0;
        #1 a = 1'b1; b = 1'b0; cin = 1'b1;
        #1 a = 1'b1; b = 1'b0; cin = 1'bx;
        #1 a = 1'b1; b = 1'b1; cin = 1'b0;
        #1 a = 1'b1; b = 1'b1; cin = 1'b1;
        #1 a = 1'b1; b = 1'b1; cin = 1'bx;
        #1 a = 1'b1; b = 1'bx; cin = 1'b0;
        #1 a = 1'b1; b = 1'bx; cin = 1'b1;
        #1 a = 1'b1; b = 1'bx; cin = 1'bx;
        #10 $finish;
    end
    initial begin
$monitor("time = %0t us, a = %b, b = %b, cin = %b, sum = %b, cout = %b", $time, a, b, cin, sum, cout);
    end
endmodule

Lab5/lab_q3.vcd
$date
	Mon Oct 16 23:41:31 2023
$end
$version
	Icarus Verilog
$end
$timescale
	1us
$end
$scope module q3_tb $end
$var wire 1 ! sum $end
$var wire 1 " cout $end
$var reg 1 # a $end
$var reg 1 $ b $end
$var reg 1 % cin $end
$scope module u1 $end
$var wire 1 # a $end
$var wire 1 $ b $end
$var wire 1 % cin $end
$var wire 1 ! sum $end
$var wire 1 " cout $end
$upscope $end
$upscope $end
$enddefinitions $end
#0
$dumpvars
x%
x$
x#
x"
x!
$end
#1
0!
0"
0%
0$
0#
#2
1!
1%
#3
x!
x"
x%
#4
1!
0"
0%
1$
#5
0!
1"
1%
#6
x!
x"
x%
#7
0%
x$
#8
1%
#9
x%
#10
1!
0"
0%
0$
1#
#11
0!
1"
1%
#12
x!
x"
x%
#13
0!
1"
0%
1$
#14
1!
1%
#15
x!
x"
x%
#16
0%
x$
#17
1%
#18
x%
