LAB2/lab2.v
module lab2(a,b,out);
input a,b;
output out;

wire w1,w2,a_bar,b_bar;

assign #0.03 a_bar=~a;
assign #0.03 b_bar=~b;

assign #1   w1 = (a & b_bar);
assign #1   w2 = (a_bar & b);
assign #1.5 out = w1 | w2;

endmodule

LAB2/lab2_tb.v
`include "lab2.v"
module lab2_tb;

reg a,b;
wire out;

lab2 obj(.a(a),.b(b),.out(out));

initial 
    begin
        $dumpfile("lab2.vcd");
        $dumpvars(0,lab2_tb);
    end

initial
    begin
        #0 a=0 ; b=0;
        #10 a=0 ; b=1;
        #10 a=1 ; b=0;
        #10 a=1 ; b=1;
        #10 $finish;
    end

endmodule

LAB2/lab2.vcd
$date
	Fri Sep 29 13:48:00 2023
$end
$version
	Icarus Verilog
$end
$timescale
	1s
$end
$scope module lab2_tb $end
$var wire 1 ! out $end
$var reg 1 " a $end
$var reg 1 # b $end
$scope module obj $end
$var wire 1 " a $end
$var wire 1 $ a_bar $end
$var wire 1 # b $end
$var wire 1 % b_bar $end
$var wire 1 ! out $end
$var wire 1 & w1 $end
$var wire 1 ' w2 $end
$upscope $end
$upscope $end
$enddefinitions $end
#0
$dumpvars
x'
x&
1%
1$
0#
0"
x!
$end
#1
0'
0&
#3
0!
#10
0%
1#
#11
1'
#13
1!
#20
1%
0$
0#
1"
#21
1&
0'
#30
0%
1#
#31
0&
#33
0!
