Lab6/as2_1.v
module Capacitor (input wire clk, output wire Q); reg state = 0;
    wire w;
    nmos sw (w, state, clk);
    always @(posedge clk)
        state <= ~state;
    assign Q = clk ? w : 1'bz;
endmodule
module Lab6_Lq1_tb;
reg clk;
    wire Q;
    Capacitor uwu(.clk(clk), .Q(Q));
    initial begin
clk = 0;
        forever #10 clk = ~clk;
    end
    initial begin
        $monitor("At time %d, clk = %b, Q = %b", $time, clk, Q);
        #100 $finish;
    end
    initial begin
        $dumpfile("Lab6_Lq1.vcd");
        $dumpvars(0, Lab6_Lq1_tb);
    end
endmodule

Lab6/Lab6_Lq1.vcd
$date
	Sun Oct 29 23:30:29 2023
$end
$version
	Icarus Verilog
$end
$timescale
	1s
$end
$scope module Lab6_Lq1_tb $end
$var wire 1 ! Q $end
$var reg 1 " clk $end
$scope module uwu $end
$var wire 1 " clk $end
$var wire 1 # w $end
$var wire 1 ! Q $end
$var reg 1 $ state $end
$upscope $end
$upscope $end
$enddefinitions $end
#0
$dumpvars
0$
z#
0"
z!
$end
#10
1$
1!
1#
1"
#20
z!
z#
0"
#30
0$
0!
0#
1"
#40
z!
z#
0"
#50
1$
1!
1#
1"
#60
z!
z#
0"
#70
0$
0!
0#
1"
#80
z!
z#
0"
#90
1$
1!
1#
1"
#100
z!
z#
0"
